LAML-1.0.2.data/scripts/extra_laml_tests.py
LAML-1.0.2.data/scripts/laml_tests.py
LAML-1.0.2.data/scripts/run_laml.py
fast_em/__init__.py
fast_em/calculations.py
fast_em/laml.py
fast_em/phylogeny.py
laml_libs/EM_solver.py
laml_libs/ML_solver.py
laml_libs/SpaLin_solver.py
laml_libs/Topology_search.py
laml_libs/Topology_search_parallel.py
laml_libs/Virtual_solver.py
laml_libs/__init__.py
laml_libs/distance_based_lib.py
laml_libs/eval_lib.py
laml_libs/fastEM_solver.py
laml_libs/lca_lib.py
laml_libs/plot_lib.py
laml_libs/sequence_lib.py
laml_libs/sim_lib.py
laml_libs/starting_tree.py
laml_libs/mixins/__init__.py
laml_libs/mixins/errors.py
laml_libs/mixins/logging.py
laml_libs/mixins/utilities.py
laml_libs/mixins/warnings.py
laml_libs/preprocess/UMI_utils.py
laml_libs/preprocess/__init__.py
laml_libs/preprocess/alignment_utilities.py
laml_libs/preprocess/cassiopeia_preprocess.py
laml_libs/preprocess/collapse_cython.py
laml_libs/preprocess/constants.py
laml_libs/preprocess/doublet_utils.py
laml_libs/preprocess/lineage_utils.py
laml_libs/preprocess/map_utils.py
laml_libs/preprocess/pipeline.py
laml_libs/preprocess/setup_utilities.py
laml_libs/preprocess/utilities.py
laml_unit_tests/__init__.py
laml_unit_tests/unit_tests_EMSolver.py
laml_unit_tests/unit_tests_MLSolver.py
laml_unit_tests/unit_tests_Simulator.py
laml_unit_tests/unit_tests_SpaLinSolver.py
laml_unit_tests/unit_tests_TopoSearch.py
laml_unit_tests/unit_tests_TopoSearchParallel.py
laml_unit_tests/unit_tests_TopoSearch_wfastEMSolver.py
laml_unit_tests/unit_tests_fastEMSolver.py
laml_unit_tests/unit_tests_io.py
laml_unit_tests/unit_tests_mosek.py
laml_unit_tests/utils.py
LAML-1.0.2.dist-info/LICENSE
LAML-1.0.2.dist-info/METADATA
LAML-1.0.2.dist-info/WHEEL
LAML-1.0.2.dist-info/entry_points.txt
LAML-1.0.2.dist-info/top_level.txt
LAML-1.0.2.dist-info/zip-safe
LAML-1.0.2.dist-info/RECORD
